smipyping/.flake8
smipyping/LICENSE.txt
smipyping/__init__.py
smipyping/_cimreport.py
smipyping/_click_configfile.py
smipyping/_click_context.py
smipyping/_cliutils.py
smipyping/_cmd_cimping.py
smipyping/_cmd_explorer.py
smipyping/_cmd_provider.gy
smipyping/_cmd_provider.py
smipyping/_cmd_sweep.py
smipyping/_cmd_targets.py
smipyping/_common.py
smipyping/_common_options.py
smipyping/_companiestable.py
smipyping/_configfile.py
smipyping/_elapsedtimer.py
smipyping/_explore.py
smipyping/_lastscantable.py
smipyping/_logging.py
smipyping/_notificationstable.py
smipyping/_ping.py
smipyping/_pingstable.py
smipyping/_previousscanstable.py
smipyping/_programstable.py
smipyping/_scanport_syn.py
smipyping/_scanport_tcp.py
smipyping/_serversweep.py
smipyping/_simpleping.py
smipyping/_tableoutput.py
smipyping/_targetdata.py
smipyping/_targetdatacli.py
smipyping/_userstable.py
smipyping/_utilities.py
smipyping/_version.py
smipyping/config.py
smipyping/cvtcvs.py
smipyping/smicli.py
smipyping/smipyping.cfg
smipyping-0.6.0.dist-info/DESCRIPTION.rst
smipyping-0.6.0.dist-info/METADATA
smipyping-0.6.0.dist-info/RECORD
smipyping-0.6.0.dist-info/WHEEL
smipyping-0.6.0.dist-info/entry_points.txt
smipyping-0.6.0.dist-info/metadata.json
smipyping-0.6.0.dist-info/pbr.json
smipyping-0.6.0.dist-info/top_level.txt
