Metadata-Version: 2.0
Name: smipyping
Version: 0.6.0
Summary: A pure Python client for SNIA SMI test support.
Home-page: https://bitbucket.com
Author: Karl Schopmeyer
Author-email: k.schopmeyer@swbell.net
License: Apache License, Version 2.0
Platform: UNKNOWN
Classifier: Development Status :: 3 - Alpha
Classifier: Environment :: Console
Classifier: Intended Audience :: Developers
Classifier: Intended Audience :: Information Technology
Classifier: License :: OSI Approved :: Apache Software License
Classifier: Operating System :: OS Independent
Classifier: Programming Language :: Python
Classifier: Programming Language :: Python :: 2
Classifier: Programming Language :: Python :: 2.7
Classifier: Programming Language :: Python :: 3
Classifier: Programming Language :: Python :: 3.4
Classifier: Programming Language :: Python :: 3.5
Classifier: Programming Language :: Python :: 3.6
Requires-Dist: click (>=6.6)
Requires-Dist: click-configfile (>=0.2.2)
Requires-Dist: click-repl (>=0.1.0)
Requires-Dist: click-spinner (>=0.1.6)
Requires-Dist: configparser (>=3.5.0)
Requires-Dist: decorator (>=4.0.10)
Requires-Dist: mysql-connector (==2.1.4)
Requires-Dist: pbr (>=1.10.0)
Requires-Dist: prompt-toolkit (>=1.0.9)
Requires-Dist: pywbem (>=0.10.0)
Requires-Dist: scapy (>-2.3.3)
Requires-Dist: six (>=1.10.0)
Requires-Dist: sqlalchemy (>=1.1.13)
Requires-Dist: tabulate (>=0.7.7)
Requires-Dist: terminaltables (>=3.1.0)
Requires-Dist: wcwidth (>=0.1.7)
